icecream/__init__.py
icecream/cli/__init__.py
icecream/cli/html_runner.py
icecream/core/__init__.py
icecream/core/assist.py
icecream/core/driver.py
icecream/core/exceptions.py
icecream/core/helper/__init__.py
icecream/core/helper/all_function.py
icecream/core/helper/encryption.py
icecream/core/helper/opredis.py
icecream/core/helper/system_function/__init__.py
icecream/core/helper/system_function/db_connection_function.py
icecream/core/helper/system_function/file_processing_function.py
icecream/core/helper/system_function/other_function.py
icecream/core/helper/system_function/random_function.py
icecream/core/helper/system_function/time_function.py
icecream/core/html_runner.py
icecream/core/mode/__init__.py
icecream/core/mode/assert_test.py
icecream/core/mode/data/__init__.py
icecream/core/mode/data/constant.py
icecream/core/mode/data/request_data.py
icecream/core/mode/env_config.py
icecream/core/mode/test_suite.py
icecream/core/protocol/__init__.py
icecream/core/protocol/http.py
icecream/core/protocol/request/__init__.py
icecream/core/protocol/request/base_request.py
icecream/core/protocol/request/factory_request.py
icecream/core/protocol/request/http_request.py
icecream/core/protocol/request/websocket_request.py
icecream/core/protocol/rpc.py
icecream/core/runner.py
icecream/core/test_result.py
icecream/ext/__init__.py
icecream/ext/ext_manage.py
icecream/ext/xray.py
icecream/resource/template/avatar2.jpg
icecream/resource/template/css/749.f86d3a03.css
icecream/resource/template/css/app.995069e3.css
icecream/resource/template/css/chunk-vendors.7d916f61.css
icecream/resource/template/css/user.57d7e17f.css
icecream/resource/template/img/background.ed05d5bd.svg
icecream/resource/template/img/logo.869e2a5e.svg
icecream/resource/template/index.html
icecream/resource/template/js/749.f927a58a.js
icecream/resource/template/js/app.379a4fec.js
icecream/resource/template/js/chunk-vendors.24c68a35.js
icecream/resource/template/js/fail.78914b43.js
icecream_cmri-1.2.9.dist-info/entry_points.txt
icecream_cmri-1.2.9.dist-info/METADATA
icecream_cmri-1.2.9.dist-info/WHEEL
icecream_cmri-1.2.9.dist-info/RECORD
