Metadata-Version: 2.3
Name: icecream_cmri
Version: 1.2.9
Summary: A framework for testing yunce offline plan
License: Apache-2.0
Author: CMRI Testing Team
Classifier: License :: OSI Approved :: Apache Software License
Classifier: Programming Language :: Python :: 2
Classifier: Programming Language :: Python :: 2.7
Classifier: Programming Language :: Python :: 3
Classifier: Programming Language :: Python :: 3.4
Classifier: Programming Language :: Python :: 3.5
Classifier: Programming Language :: Python :: 3.6
Classifier: Programming Language :: Python :: 3.7
Classifier: Programming Language :: Python :: 3.8
Classifier: Programming Language :: Python :: 3.9
Classifier: Programming Language :: Python :: 3.10
Classifier: Programming Language :: Python :: 3.11
Classifier: Programming Language :: Python :: 3.12
Classifier: Programming Language :: Python :: 3.13
Requires-Dist: PyYAML (>5.1.2)
Requires-Dist: chardet (>=4.0.0,<5.0.0)
Requires-Dist: jmespath (>=0.9.0,<0.10.0)
Requires-Dist: jsonpath (>=0.82,<0.83)
Requires-Dist: jsonschema (>=3.2.0,<4.0.0)
Requires-Dist: openpyxl (>=3.0.10,<4.0.0)
Requires-Dist: pandas (>=2.2.3)
Requires-Dist: psutil (>=6.1.0,<7.0.0)
Requires-Dist: pycryptodome (>=3.10.1,<4.0.0)
Requires-Dist: pymongo (>=4.1.1,<5.0.0)
Requires-Dist: pymysql (>=1.0.2,<2.0.0)
Requires-Dist: python-docx (>=1.0.1)
Requires-Dist: python-ulid (>=3.0.0)
Requires-Dist: redis-py-cluster (>=2.1.3,<3.0.0)
Requires-Dist: requests (>=2.27.1,<3.0.0)
Requires-Dist: requests-toolbelt (>=1.0.0)
Requires-Dist: six (>=1.16.0,<2.0.0)
Requires-Dist: websocket-client (>=1.3.1,<2.0.0)
Requires-Dist: websockets (>=12.0)
